{
  "last_updated": "2025-06-15T02:28:16.692424+00:00",
  "levels": {
    "Binance_COSUSDT_perp_1M": {
      "exchange": "Binance",
      "symbol": "COSUSDT",
      "market": "perp",
      "interval": "1M",
      "price": 0.003652,
      "signal_type": "bearish",
      "timestamp": "2025-06-15T02:28:17.744360+00:00"
    },
    "Binance_MANAUSDT_perp_1M": {
      "exchange": "Binance",
      "symbol": "MANAUSDT",
      "market": "perp",
      "interval": "1M",
      "price": 0.3155,
      "signal_type": "bearish",
      "timestamp": "2025-06-15T02:28:20.697413+00:00"
    },
    "Binance_AKTUSDT_perp_1M": {
      "exchange": "Binance",
      "symbol": "AKTUSDT",
      "market": "perp",
      "interval": "1M",
      "price": 1.462,
      "signal_type": "bearish",
      "timestamp": "2025-06-15T02:28:21.951406+00:00"
    },
    "Binance_BABYUSDT_perp_1M": {
      "exchange": "Binance",
      "symbol": "BABYUSDT",
      "market": "perp",
      "interval": "1M",
      "price": 0.10508,
      "signal_type": "bearish",
      "timestamp": "2025-06-15T02:28:23.044366+00:00"
    },
    "Binance_HYPERUSDT_perp_1d": {
      "exchange": "Binance",
      "symbol": "HYPERUSDT",
      "market": "perp",
      "interval": "1d",
      "price": 0.1128,
      "signal_type": "bullish",
      "timestamp": "2025-06-15T02:28:24.056715+00:00"
    },
    "Binance_STORJUSDT_perp_1M": {
      "exchange": "Binance",
      "symbol": "STORJUSDT",
      "market": "perp",
      "interval": "1M",
      "price": 0.3063,
      "signal_type": "bearish",
      "timestamp": "2025-06-15T02:28:30.671334+00:00"
    },
    "Binance_AWEUSDT_perp_1d": {
      "exchange": "Binance",
      "symbol": "AWEUSDT",
      "market": "perp",
      "interval": "1d",
      "price": 0.052923,
      "signal_type": "bearish",
      "timestamp": "2025-06-15T02:28:31.745121+00:00"
    },
    "Binance_PHAUSDT_perp_1w": {
      "exchange": "Binance",
      "symbol": "PHAUSDT",
      "market": "perp",
      "interval": "1w",
      "price": 0.13466,
      "signal_type": "bearish",
      "timestamp": "2025-06-15T02:28:32.765290+00:00"
    },
    "Binance_PARTIUSDT_perp_1M": {
      "exchange": "Binance",
      "symbol": "PARTIUSDT",
      "market": "perp",
      "interval": "1M",
      "price": 0.2098,
      "signal_type": "bullish",
      "timestamp": "2025-06-15T02:28:33.755040+00:00"
    },
    "Binance_GASUSDT_perp_1M": {
      "exchange": "Binance",
      "symbol": "GASUSDT",
      "market": "perp",
      "interval": "1M",
      "price": 3.291,
      "signal_type": "bearish",
      "timestamp": "2025-06-15T02:28:47.821777+00:00"
    },
    "Binance_BTCUSDT_perp_1d": {
      "exchange": "Binance",
      "symbol": "BTCUSDT",
      "market": "perp",
      "interval": "1d",
      "price": 106027.3,
      "signal_type": "bearish",
      "timestamp": "2025-06-15T02:28:49.883649+00:00"
    },
    "Binance_TRUMPUSDT_perp_1M": {
      "exchange": "Binance",
      "symbol": "TRUMPUSDT",
      "market": "perp",
      "interval": "1M",
      "price": 13.158,
      "signal_type": "bearish",
      "timestamp": "2025-06-15T02:28:50.866536+00:00"
    },
    "Binance_DEGENUSDT_perp_1d": {
      "exchange": "Binance",
      "symbol": "DEGENUSDT",
      "market": "perp",
      "interval": "1d",
      "price": 0.00401,
      "signal_type": "bearish",
      "timestamp": "2025-06-15T02:29:05.062127+00:00"
    },
    "Binance_OMUSDT_perp_1d": {
      "exchange": "Binance",
      "symbol": "OMUSDT",
      "market": "perp",
      "interval": "1d",
      "price": 0.26126,
      "signal_type": "bullish",
      "timestamp": "2025-06-15T02:29:06.417795+00:00"
    },
    "Binance_HIFIUSDT_perp_1M": {
      "exchange": "Binance",
      "symbol": "HIFIUSDT",
      "market": "perp",
      "interval": "1M",
      "price": 0.2682,
      "signal_type": "bearish",
      "timestamp": "2025-06-15T02:29:07.259813+00:00"
    },
    "Binance_PORTALUSDT_perp_1M": {
      "exchange": "Binance",
      "symbol": "PORTALUSDT",
      "market": "perp",
      "interval": "1M",
      "price": 0.0894,
      "signal_type": "bearish",
      "timestamp": "2025-06-15T02:29:21.417697+00:00"
    },
    "Binance_BNBUSDT_perp_1M": {
      "exchange": "Binance",
      "symbol": "BNBUSDT",
      "market": "perp",
      "interval": "1M",
      "price": 599.21,
      "signal_type": "bullish",
      "timestamp": "2025-06-15T02:29:22.529442+00:00"
    },
    "Binance_ARCUSDT_perp_1M": {
      "exchange": "Binance",
      "symbol": "ARCUSDT",
      "market": "perp",
      "interval": "1M",
      "price": 0.05911,
      "signal_type": "bearish",
      "timestamp": "2025-06-15T02:29:23.171232+00:00"
    },
    "Binance_WAXPUSDT_perp_1M": {
      "exchange": "Binance",
      "symbol": "WAXPUSDT",
      "market": "perp",
      "interval": "1M",
      "price": 0.02434,
      "signal_type": "bearish",
      "timestamp": "2025-06-15T02:29:24.207687+00:00"
    },
    "Binance_OPUSDT_perp_1d": {
      "exchange": "Binance",
      "symbol": "OPUSDT",
      "market": "perp",
      "interval": "1d",
      "price": 0.5898,
      "signal_type": "bullish",
      "timestamp": "2025-06-15T02:29:25.507729+00:00"
    },
    "Binance_ZEREBROUSDT_perp_1d": {
      "exchange": "Binance",
      "symbol": "ZEREBROUSDT",
      "market": "perp",
      "interval": "1d",
      "price": 0.02846,
      "signal_type": "bearish",
      "timestamp": "2025-06-15T02:29:26.154181+00:00"
    },
    "Binance_ETHUSDT_perp_1M": {
      "exchange": "Binance",
      "symbol": "ETHUSDT",
      "market": "perp",
      "interval": "1M",
      "price": 1792.71,
      "signal_type": "bullish",
      "timestamp": "2025-06-15T02:29:27.164731+00:00"
    },
    "Binance_SHELLUSDT_perp_1M": {
      "exchange": "Binance",
      "symbol": "SHELLUSDT",
      "market": "perp",
      "interval": "1M",
      "price": 0.2269,
      "signal_type": "bearish",
      "timestamp": "2025-06-15T02:29:28.179266+00:00"
    },
    "Binance_UMAUSDT_perp_1w": {
      "exchange": "Binance",
      "symbol": "UMAUSDT",
      "market": "perp",
      "interval": "1w",
      "price": 1.131,
      "signal_type": "bullish",
      "timestamp": "2025-06-15T02:29:28.768871+00:00"
    },
    "Binance_AIOTUSDT_perp_1d": {
      "exchange": "Binance",
      "symbol": "AIOTUSDT",
      "market": "perp",
      "interval": "1d",
      "price": 0.11829,
      "signal_type": "bullish",
      "timestamp": "2025-06-15T02:29:29.709242+00:00"
    },
    "Binance_ZRXUSDT_perp_1M": {
      "exchange": "Binance",
      "symbol": "ZRXUSDT",
      "market": "perp",
      "interval": "1M",
      "price": 0.2777,
      "signal_type": "bearish",
      "timestamp": "2025-06-15T02:29:30.727184+00:00"
    },
    "Binance_BRETTUSDT_perp_1M": {
      "exchange": "Binance",
      "symbol": "BRETTUSDT",
      "market": "perp",
      "interval": "1M",
      "price": 0.06217,
      "signal_type": "bearish",
      "timestamp": "2025-06-15T02:29:31.331279+00:00"
    },
    "Binance_BIDUSDT_perp_1w": {
      "exchange": "Binance",
      "symbol": "BIDUSDT",
      "market": "perp",
      "interval": "1w",
      "price": 0.03601,
      "signal_type": "bullish",
      "timestamp": "2025-06-15T02:29:32.235042+00:00"
    },
    "Binance_SPELLUSDT_perp_1M": {
      "exchange": "Binance",
      "symbol": "SPELLUSDT",
      "market": "perp",
      "interval": "1M",
      "price": 0.0005887,
      "signal_type": "bearish",
      "timestamp": "2025-06-15T02:29:33.508079+00:00"
    },
    "Binance_DENTUSDT_perp_1M": {
      "exchange": "Binance",
      "symbol": "DENTUSDT",
      "market": "perp",
      "interval": "1M",
      "price": 0.000819,
      "signal_type": "bearish",
      "timestamp": "2025-06-15T02:29:34.091768+00:00"
    },
    "Binance_ONEUSDT_perp_1M": {
      "exchange": "Binance",
      "symbol": "ONEUSDT",
      "market": "perp",
      "interval": "1M",
      "price": 0.01343,
      "signal_type": "bearish",
      "timestamp": "2025-06-15T02:29:35.008623+00:00"
    },
    "Binance_TRBUSDT_perp_1d": {
      "exchange": "Binance",
      "symbol": "TRBUSDT",
      "market": "perp",
      "interval": "1d",
      "price": 42.088,
      "signal_type": "bearish",
      "timestamp": "2025-06-15T02:29:37.075204+00:00"
    },
    "Binance_LTCUSDT_perp_1d": {
      "exchange": "Binance",
      "symbol": "LTCUSDT",
      "market": "perp",
      "interval": "1d",
      "price": 86.47,
      "signal_type": "bearish",
      "timestamp": "2025-06-15T02:29:37.662761+00:00"
    },
    "Binance_TWTUSDT_perp_1d": {
      "exchange": "Binance",
      "symbol": "TWTUSDT",
      "market": "perp",
      "interval": "1d",
      "price": 0.784,
      "signal_type": "bearish",
      "timestamp": "2025-06-15T02:29:38.613617+00:00"
    },
    "Binance_BMTUSDT_perp_1M": {
      "exchange": "Binance",
      "symbol": "BMTUSDT",
      "market": "perp",
      "interval": "1M",
      "price": 0.1388,
      "signal_type": "bearish",
      "timestamp": "2025-06-15T02:29:39.878393+00:00"
    },
    "Binance_APTUSDT_perp_1M": {
      "exchange": "Binance",
      "symbol": "APTUSDT",
      "market": "perp",
      "interval": "1M",
      "price": 5.3436,
      "signal_type": "bearish",
      "timestamp": "2025-06-15T02:29:40.467866+00:00"
    },
    "Binance_NFPUSDT_perp_1M": {
      "exchange": "Binance",
      "symbol": "NFPUSDT",
      "market": "perp",
      "interval": "1M",
      "price": 0.0878,
      "signal_type": "bearish",
      "timestamp": "2025-06-15T02:29:41.667652+00:00"
    },
    "Binance_RSRUSDT_perp_1M": {
      "exchange": "Binance",
      "symbol": "RSRUSDT",
      "market": "perp",
      "interval": "1M",
      "price": 0.009029,
      "signal_type": "bearish",
      "timestamp": "2025-06-15T02:29:43.969744+00:00"
    },
    "Binance_FUNUSDT_perp_1M": {
      "exchange": "Binance",
      "symbol": "FUNUSDT",
      "market": "perp",
      "interval": "1M",
      "price": 0.005446,
      "signal_type": "bearish",
      "timestamp": "2025-06-15T02:29:44.552280+00:00"
    },
    "Binance_ZECUSDT_perp_1M": {
      "exchange": "Binance",
      "symbol": "ZECUSDT",
      "market": "perp",
      "interval": "1M",
      "price": 36.0,
      "signal_type": "bullish",
      "timestamp": "2025-06-15T02:29:45.787703+00:00"
    },
    "Binance_BUSDT_perp_1w": {
      "exchange": "Binance",
      "symbol": "BUSDT",
      "market": "perp",
      "interval": "1w",
      "price": 0.40154,
      "signal_type": "bearish",
      "timestamp": "2025-06-15T02:29:46.841046+00:00"
    },
    "Binance_FUNUSDT_perp_1d": {
      "exchange": "Binance",
      "symbol": "FUNUSDT",
      "market": "perp",
      "interval": "1d",
      "price": 0.003986,
      "signal_type": "bearish",
      "timestamp": "2025-06-15T02:29:47.452801+00:00"
    },
    "Binance_FISUSDT_perp_1M": {
      "exchange": "Binance",
      "symbol": "FISUSDT",
      "market": "perp",
      "interval": "1M",
      "price": 0.2495,
      "signal_type": "bearish",
      "timestamp": "2025-06-15T02:29:48.368560+00:00"
    },
    "Binance_YGGUSDT_perp_1M": {
      "exchange": "Binance",
      "symbol": "YGGUSDT",
      "market": "perp",
      "interval": "1M",
      "price": 0.2091,
      "signal_type": "bearish",
      "timestamp": "2025-06-15T02:29:49.707224+00:00"
    },
    "Binance_SYSUSDT_perp_1M": {
      "exchange": "Binance",
      "symbol": "SYSUSDT",
      "market": "perp",
      "interval": "1M",
      "price": 0.05126,
      "signal_type": "bearish",
      "timestamp": "2025-06-15T02:29:50.917870+00:00"
    },
    "Binance_ALGOUSDT_perp_1M": {
      "exchange": "Binance",
      "symbol": "ALGOUSDT",
      "market": "perp",
      "interval": "1M",
      "price": 0.2199,
      "signal_type": "bearish",
      "timestamp": "2025-06-15T02:29:52.176631+00:00"
    },
    "Binance_ACHUSDT_perp_1M": {
      "exchange": "Binance",
      "symbol": "ACHUSDT",
      "market": "perp",
      "interval": "1M",
      "price": 0.027106,
      "signal_type": "bearish",
      "timestamp": "2025-06-15T02:29:53.199670+00:00"
    },
    "Binance_DRIFTUSDT_perp_1M": {
      "exchange": "Binance",
      "symbol": "DRIFTUSDT",
      "market": "perp",
      "interval": "1M",
      "price": 0.7019,
      "signal_type": "bearish",
      "timestamp": "2025-06-15T02:29:53.785519+00:00"
    },
    "Binance_ICPUSDT_perp_1w": {
      "exchange": "Binance",
      "symbol": "ICPUSDT",
      "market": "perp",
      "interval": "1w",
      "price": 4.935,
      "signal_type": "bullish",
      "timestamp": "2025-06-15T02:29:55.047775+00:00"
    },
    "Binance_AI16ZUSDT_perp_1M": {
      "exchange": "Binance",
      "symbol": "AI16ZUSDT",
      "market": "perp",
      "interval": "1M",
      "price": 0.2761,
      "signal_type": "bearish",
      "timestamp": "2025-06-15T02:29:56.062805+00:00"
    },
    "Binance_KAVAUSDT_perp_1d": {
      "exchange": "Binance",
      "symbol": "KAVAUSDT",
      "market": "perp",
      "interval": "1d",
      "price": 0.4247,
      "signal_type": "bearish",
      "timestamp": "2025-06-15T02:29:56.636142+00:00"
    },
    "Binance_ETHWUSDT_perp_1d": {
      "exchange": "Binance",
      "symbol": "ETHWUSDT",
      "market": "perp",
      "interval": "1d",
      "price": 1.4221,
      "signal_type": "bearish",
      "timestamp": "2025-06-15T02:29:57.640515+00:00"
    },
    "Binance_SEIUSDT_perp_1M": {
      "exchange": "Binance",
      "symbol": "SEIUSDT",
      "market": "perp",
      "interval": "1M",
      "price": 0.212,
      "signal_type": "bearish",
      "timestamp": "2025-06-15T02:29:59.742499+00:00"
    },
    "Binance_SONICUSDT_perp_1d": {
      "exchange": "Binance",
      "symbol": "SONICUSDT",
      "market": "perp",
      "interval": "1d",
      "price": 0.2156,
      "signal_type": "bearish",
      "timestamp": "2025-06-15T02:30:00.339179+00:00"
    },
    "Binance_LAUSDT_perp_1d": {
      "exchange": "Binance",
      "symbol": "LAUSDT",
      "market": "perp",
      "interval": "1d",
      "price": 0.851,
      "signal_type": "bearish",
      "timestamp": "2025-06-15T02:30:01.428574+00:00"
    },
    "Binance_RENDERUSDT_perp_1M": {
      "exchange": "Binance",
      "symbol": "RENDERUSDT",
      "market": "perp",
      "interval": "1M",
      "price": 4.455,
      "signal_type": "bearish",
      "timestamp": "2025-06-15T02:30:02.503957+00:00"
    },
    "Binance_BANDUSDT_perp_1d": {
      "exchange": "Binance",
      "symbol": "BANDUSDT",
      "market": "perp",
      "interval": "1d",
      "price": 0.6248,
      "signal_type": "bullish",
      "timestamp": "2025-06-15T02:30:04.021942+00:00"
    },
    "Binance_SXPUSDT_perp_1M": {
      "exchange": "Binance",
      "symbol": "SXPUSDT",
      "market": "perp",
      "interval": "1M",
      "price": 0.2036,
      "signal_type": "bearish",
      "timestamp": "2025-06-15T02:30:05.099164+00:00"
    },
    "Binance_BATUSDT_perp_1M": {
      "exchange": "Binance",
      "symbol": "BATUSDT",
      "market": "perp",
      "interval": "1M",
      "price": 0.1523,
      "signal_type": "bearish",
      "timestamp": "2025-06-15T02:30:07.248224+00:00"
    },
    "Binance_IOTAUSDT_perp_1M": {
      "exchange": "Binance",
      "symbol": "IOTAUSDT",
      "market": "perp",
      "interval": "1M",
      "price": 0.2064,
      "signal_type": "bearish",
      "timestamp": "2025-06-15T02:30:07.945956+00:00"
    },
    "Binance_COMPUSDT_perp_1w": {
      "exchange": "Binance",
      "symbol": "COMPUSDT",
      "market": "perp",
      "interval": "1w",
      "price": 40.73,
      "signal_type": "bullish",
      "timestamp": "2025-06-15T02:30:08.870828+00:00"
    },
    "Binance_SIGNUSDT_perp_1M": {
      "exchange": "Binance",
      "symbol": "SIGNUSDT",
      "market": "perp",
      "interval": "1M",
      "price": 0.09541,
      "signal_type": "bearish",
      "timestamp": "2025-06-15T02:30:09.899452+00:00"
    },
    "Binance_COMPUSDT_perp_1d": {
      "exchange": "Binance",
      "symbol": "COMPUSDT",
      "market": "perp",
      "interval": "1d",
      "price": 56.03,
      "signal_type": "bearish",
      "timestamp": "2025-06-15T02:30:11.106674+00:00"
    },
    "Binance_SCRTUSDT_perp_1M": {
      "exchange": "Binance",
      "symbol": "SCRTUSDT",
      "market": "perp",
      "interval": "1M",
      "price": 0.2133,
      "signal_type": "bearish",
      "timestamp": "2025-06-15T02:30:12.358585+00:00"
    },
    "Binance_SCRUSDT_perp_1M": {
      "exchange": "Binance",
      "symbol": "SCRUSDT",
      "market": "perp",
      "interval": "1M",
      "price": 0.3493,
      "signal_type": "bearish",
      "timestamp": "2025-06-15T02:30:13.407841+00:00"
    },
    "Binance_SFPUSDT_perp_1M": {
      "exchange": "Binance",
      "symbol": "SFPUSDT",
      "market": "perp",
      "interval": "1M",
      "price": 0.5275,
      "signal_type": "bearish",
      "timestamp": "2025-06-15T02:30:15.178518+00:00"
    },
    "Binance_AEVOUSDT_perp_1M": {
      "exchange": "Binance",
      "symbol": "AEVOUSDT",
      "market": "perp",
      "interval": "1M",
      "price": 0.1116,
      "signal_type": "bearish",
      "timestamp": "2025-06-15T02:30:16.117841+00:00"
    },
    "Binance_SKYAIUSDT_perp_1d": {
      "exchange": "Binance",
      "symbol": "SKYAIUSDT",
      "market": "perp",
      "interval": "1d",
      "price": 0.03273,
      "signal_type": "bearish",
      "timestamp": "2025-06-15T02:30:17.134188+00:00"
    },
    "Binance_WUSDT_perp_1M": {
      "exchange": "Binance",
      "symbol": "WUSDT",
      "market": "perp",
      "interval": "1M",
      "price": 0.0873,
      "signal_type": "bearish",
      "timestamp": "2025-06-15T02:30:20.367103+00:00"
    },
    "Binance_FLOWUSDT_perp_1M": {
      "exchange": "Binance",
      "symbol": "FLOWUSDT",
      "market": "perp",
      "interval": "1M",
      "price": 0.402,
      "signal_type": "bearish",
      "timestamp": "2025-06-15T02:30:21.448833+00:00"
    },
    "Binance_AIXBTUSDT_perp_1d": {
      "exchange": "Binance",
      "symbol": "AIXBTUSDT",
      "market": "perp",
      "interval": "1d",
      "price": 0.17297,
      "signal_type": "bearish",
      "timestamp": "2025-06-15T02:30:22.470101+00:00"
    },
    "Binance_ANKRUSDT_perp_1M": {
      "exchange": "Binance",
      "symbol": "ANKRUSDT",
      "market": "perp",
      "interval": "1M",
      "price": 0.01979,
      "signal_type": "bearish",
      "timestamp": "2025-06-15T02:30:25.924632+00:00"
    },
    "Binance_TRUUSDT_perp_1M": {
      "exchange": "Binance",
      "symbol": "TRUUSDT",
      "market": "perp",
      "interval": "1M",
      "price": 0.04021,
      "signal_type": "bearish",
      "timestamp": "2025-06-15T02:30:27.390912+00:00"
    },
    "Binance_NOTUSDT_perp_1M": {
      "exchange": "Binance",
      "symbol": "NOTUSDT",
      "market": "perp",
      "interval": "1M",
      "price": 0.002607,
      "signal_type": "bearish",
      "timestamp": "2025-06-15T02:30:29.473689+00:00"
    },
    "Binance_ACEUSDT_perp_1M": {
      "exchange": "Binance",
      "symbol": "ACEUSDT",
      "market": "perp",
      "interval": "1M",
      "price": 0.6762,
      "signal_type": "bearish",
      "timestamp": "2025-06-15T02:30:31.821227+00:00"
    },
    "Binance_TUSDT_perp_1M": {
      "exchange": "Binance",
      "symbol": "TUSDT",
      "market": "perp",
      "interval": "1M",
      "price": 0.01765,
      "signal_type": "bearish",
      "timestamp": "2025-06-15T02:30:33.436822+00:00"
    },
    "Binance_ARKUSDT_perp_1M": {
      "exchange": "Binance",
      "symbol": "ARKUSDT",
      "market": "perp",
      "interval": "1M",
      "price": 0.4368,
      "signal_type": "bearish",
      "timestamp": "2025-06-15T02:30:34.484560+00:00"
    },
    "Binance_MASKUSDT_perp_1M": {
      "exchange": "Binance",
      "symbol": "MASKUSDT",
      "market": "perp",
      "interval": "1M",
      "price": 1.1782,
      "signal_type": "bullish",
      "timestamp": "2025-06-15T02:30:38.479230+00:00"
    },
    "Binance_DUSKUSDT_perp_1M": {
      "exchange": "Binance",
      "symbol": "DUSKUSDT",
      "market": "perp",
      "interval": "1M",
      "price": 0.0861,
      "signal_type": "bearish",
      "timestamp": "2025-06-15T02:30:40.253754+00:00"
    },
    "Binance_PUMPBTCUSDT_perp_1d": {
      "exchange": "Binance",
      "symbol": "PUMPBTCUSDT",
      "market": "perp",
      "interval": "1d",
      "price": 0.04985,
      "signal_type": "bearish",
      "timestamp": "2025-06-15T02:30:41.259625+00:00"
    },
    "Binance_ACEUSDT_perp_1d": {
      "exchange": "Binance",
      "symbol": "ACEUSDT",
      "market": "perp",
      "interval": "1d",
      "price": 0.5537,
      "signal_type": "bullish",
      "timestamp": "2025-06-15T02:30:46.645924+00:00"
    },
    "Binance_BICOUSDT_perp_1M": {
      "exchange": "Binance",
      "symbol": "BICOUSDT",
      "market": "perp",
      "interval": "1M",
      "price": 0.1335,
      "signal_type": "bearish",
      "timestamp": "2025-06-15T02:30:47.908710+00:00"
    },
    "Binance_NMRUSDT_perp_1M": {
      "exchange": "Binance",
      "symbol": "NMRUSDT",
      "market": "perp",
      "interval": "1M",
      "price": 9.174,
      "signal_type": "bearish",
      "timestamp": "2025-06-15T02:30:49.203866+00:00"
    },
    "Binance_DEXEUSDT_perp_1d": {
      "exchange": "Binance",
      "symbol": "DEXEUSDT",
      "market": "perp",
      "interval": "1d",
      "price": 8.952,
      "signal_type": "bearish",
      "timestamp": "2025-06-15T02:30:50.557538+00:00"
    },
    "Binance_DEGOUSDT_perp_1w": {
      "exchange": "Binance",
      "symbol": "DEGOUSDT",
      "market": "perp",
      "interval": "1w",
      "price": 2.6746,
      "signal_type": "bearish",
      "timestamp": "2025-06-15T02:30:51.494577+00:00"
    },
    "Binance_PROMPTUSDT_perp_1M": {
      "exchange": "Binance",
      "symbol": "PROMPTUSDT",
      "market": "perp",
      "interval": "1M",
      "price": 0.3934,
      "signal_type": "bearish",
      "timestamp": "2025-06-15T02:30:52.861299+00:00"
    },
    "Binance_ANIMEUSDT_perp_1d": {
      "exchange": "Binance",
      "symbol": "ANIMEUSDT",
      "market": "perp",
      "interval": "1d",
      "price": 0.02388,
      "signal_type": "bullish",
      "timestamp": "2025-06-15T02:30:54.186664+00:00"
    },
    "Binance_EGLDUSDT_perp_1M": {
      "exchange": "Binance",
      "symbol": "EGLDUSDT",
      "market": "perp",
      "interval": "1M",
      "price": 17.208,
      "signal_type": "bearish",
      "timestamp": "2025-06-15T02:30:55.333389+00:00"
    },
    "Binance_DEGOUSDT_perp_1d": {
      "exchange": "Binance",
      "symbol": "DEGOUSDT",
      "market": "perp",
      "interval": "1d",
      "price": 1.0852,
      "signal_type": "bullish",
      "timestamp": "2025-06-15T02:30:56.381306+00:00"
    },
    "Binance_PROMPTUSDT_perp_1d": {
      "exchange": "Binance",
      "symbol": "PROMPTUSDT",
      "market": "perp",
      "interval": "1d",
      "price": 0.1652,
      "signal_type": "bearish",
      "timestamp": "2025-06-15T02:30:58.563055+00:00"
    },
    "Binance_ATAUSDT_perp_1M": {
      "exchange": "Binance",
      "symbol": "ATAUSDT",
      "market": "perp",
      "interval": "1M",
      "price": 0.0615,
      "signal_type": "bearish",
      "timestamp": "2025-06-15T02:30:59.865688+00:00"
    },
    "Binance_STEEMUSDT_perp_1M": {
      "exchange": "Binance",
      "symbol": "STEEMUSDT",
      "market": "perp",
      "interval": "1M",
      "price": 0.15081,
      "signal_type": "bearish",
      "timestamp": "2025-06-15T02:31:00.890566+00:00"
    },
    "Binance_CYBERUSDT_perp_1d": {
      "exchange": "Binance",
      "symbol": "CYBERUSDT",
      "market": "perp",
      "interval": "1d",
      "price": 1.263,
      "signal_type": "bearish",
      "timestamp": "2025-06-15T02:31:02.193850+00:00"
    },
    "Binance_BSVUSDT_perp_1M": {
      "exchange": "Binance",
      "symbol": "BSVUSDT",
      "market": "perp",
      "interval": "1M",
      "price": 37.95,
      "signal_type": "bearish",
      "timestamp": "2025-06-15T02:31:03.171183+00:00"
    },
    "Binance_FIOUSDT_perp_1M": {
      "exchange": "Binance",
      "symbol": "FIOUSDT",
      "market": "perp",
      "interval": "1M",
      "price": 0.01858,
      "signal_type": "bearish",
      "timestamp": "2025-06-15T02:31:04.227564+00:00"
    },
    "Binance_RLCUSDT_perp_1M": {
      "exchange": "Binance",
      "symbol": "RLCUSDT",
      "market": "perp",
      "interval": "1M",
      "price": 1.2189,
      "signal_type": "bearish",
      "timestamp": "2025-06-15T02:31:10.930225+00:00"
    },
    "Binance_ONTUSDT_perp_1M": {
      "exchange": "Binance",
      "symbol": "ONTUSDT",
      "market": "perp",
      "interval": "1M",
      "price": 0.1536,
      "signal_type": "bearish",
      "timestamp": "2025-06-15T02:31:11.973580+00:00"
    },
    "Binance_LAYERUSDT_perp_1M": {
      "exchange": "Binance",
      "symbol": "LAYERUSDT",
      "market": "perp",
      "interval": "1M",
      "price": 3.0374,
      "signal_type": "bearish",
      "timestamp": "2025-06-15T02:31:14.458597+00:00"
    },
    "Binance_BSVUSDT_perp_1d": {
      "exchange": "Binance",
      "symbol": "BSVUSDT",
      "market": "perp",
      "interval": "1d",
      "price": 31.22,
      "signal_type": "bearish",
      "timestamp": "2025-06-15T02:31:15.498824+00:00"
    },
    "Binance_GMTUSDT_perp_1M": {
      "exchange": "Binance",
      "symbol": "GMTUSDT",
      "market": "perp",
      "interval": "1M",
      "price": 0.05767,
      "signal_type": "bearish",
      "timestamp": "2025-06-15T02:31:16.514509+00:00"
    },
    "Binance_JELLYJELLYUSDT_perp_1d": {
      "exchange": "Binance",
      "symbol": "JELLYJELLYUSDT",
      "market": "perp",
      "interval": "1d",
      "price": 0.03301,
      "signal_type": "bearish",
      "timestamp": "2025-06-15T02:31:17.498215+00:00"
    },
    "Binance_C98USDT_perp_1d": {
      "exchange": "Binance",
      "symbol": "C98USDT",
      "market": "perp",
      "interval": "1d",
      "price": 0.0478,
      "signal_type": "bullish",
      "timestamp": "2025-06-15T02:31:18.588785+00:00"
    },
    "Binance_PORTOUSDT_spot_1d": {
      "exchange": "Binance",
      "symbol": "PORTOUSDT",
      "market": "spot",
      "interval": "1d",
      "price": 0.841,
      "signal_type": "bullish",
      "timestamp": "2025-06-15T02:31:19.719296+00:00"
    },
    "Binance_ACAUSDT_spot_1d": {
      "exchange": "Binance",
      "symbol": "ACAUSDT",
      "market": "spot",
      "interval": "1d",
      "price": 0.0264,
      "signal_type": "bullish",
      "timestamp": "2025-06-15T02:31:21.023274+00:00"
    },
    "Binance_GNSUSDT_spot_1M": {
      "exchange": "Binance",
      "symbol": "GNSUSDT",
      "market": "spot",
      "interval": "1M",
      "price": 1.508,
      "signal_type": "bearish",
      "timestamp": "2025-06-15T02:31:21.947544+00:00"
    },
    "Binance_IDEXUSDT_spot_1M": {
      "exchange": "Binance",
      "symbol": "IDEXUSDT",
      "market": "spot",
      "interval": "1M",
      "price": 0.02613,
      "signal_type": "bearish",
      "timestamp": "2025-06-15T02:31:22.965508+00:00"
    },
    "Binance_RADUSDT_spot_1M": {
      "exchange": "Binance",
      "symbol": "RADUSDT",
      "market": "spot",
      "interval": "1M",
      "price": 0.8,
      "signal_type": "bearish",
      "timestamp": "2025-06-15T02:31:23.997341+00:00"
    },
    "Binance_BONKUSDT_spot_1M": {
      "exchange": "Binance",
      "symbol": "BONKUSDT",
      "market": "spot",
      "interval": "1M",
      "price": 1.95e-05,
      "signal_type": "bearish",
      "timestamp": "2025-06-15T02:31:25.005034+00:00"
    },
    "Binance_PIVXUSDT_spot_1M": {
      "exchange": "Binance",
      "symbol": "PIVXUSDT",
      "market": "spot",
      "interval": "1M",
      "price": 0.1602,
      "signal_type": "bearish",
      "timestamp": "2025-06-15T02:31:26.090000+00:00"
    },
    "Binance_PYRUSDT_spot_1d": {
      "exchange": "Binance",
      "symbol": "PYRUSDT",
      "market": "spot",
      "interval": "1d",
      "price": 1.014,
      "signal_type": "bearish",
      "timestamp": "2025-06-15T02:31:28.831062+00:00"
    },
    "Binance_RADUSDT_spot_1d": {
      "exchange": "Binance",
      "symbol": "RADUSDT",
      "market": "spot",
      "interval": "1d",
      "price": 0.673,
      "signal_type": "bullish",
      "timestamp": "2025-06-15T02:31:29.838947+00:00"
    },
    "Binance_BARUSDT_spot_1M": {
      "exchange": "Binance",
      "symbol": "BARUSDT",
      "market": "spot",
      "interval": "1M",
      "price": 2.155,
      "signal_type": "bearish",
      "timestamp": "2025-06-15T02:31:30.863952+00:00"
    },
    "Binance_NEXOUSDT_spot_1d": {
      "exchange": "Binance",
      "symbol": "NEXOUSDT",
      "market": "spot",
      "interval": "1d",
      "price": 1.228,
      "signal_type": "bearish",
      "timestamp": "2025-06-15T02:31:35.851871+00:00"
    },
    "Binance_SLPUSDT_spot_1M": {
      "exchange": "Binance",
      "symbol": "SLPUSDT",
      "market": "spot",
      "interval": "1M",
      "price": 0.001725,
      "signal_type": "bearish",
      "timestamp": "2025-06-15T02:31:36.916206+00:00"
    },
    "Bybit_NSUSDT_perp_1M": {
      "exchange": "Bybit",
      "symbol": "NSUSDT",
      "market": "perp",
      "interval": "1M",
      "price": 0.2194,
      "signal_type": "bearish",
      "timestamp": "2025-06-15T02:31:37.785225+00:00"
    },
    "Bybit_COOKUSDT_perp_1M": {
      "exchange": "Bybit",
      "symbol": "COOKUSDT",
      "market": "perp",
      "interval": "1M",
      "price": 0.007965,
      "signal_type": "bullish",
      "timestamp": "2025-06-15T02:31:38.773810+00:00"
    },
    "Binance_MBLUSDT_spot_1d": {
      "exchange": "Binance",
      "symbol": "MBLUSDT",
      "market": "spot",
      "interval": "1d",
      "price": 0.002212,
      "signal_type": "bullish",
      "timestamp": "2025-06-15T02:31:39.683132+00:00"
    },
    "Bybit_COOKUSDT_perp_1w": {
      "exchange": "Bybit",
      "symbol": "COOKUSDT",
      "market": "perp",
      "interval": "1w",
      "price": 0.009465,
      "signal_type": "bearish",
      "timestamp": "2025-06-15T02:31:40.695917+00:00"
    },
    "Bybit_BALUSDT_perp_1M": {
      "exchange": "Bybit",
      "symbol": "BALUSDT",
      "market": "perp",
      "interval": "1M",
      "price": 0.934,
      "signal_type": "bullish",
      "timestamp": "2025-06-15T02:31:41.557697+00:00"
    },
    "Bybit_CROUSDT_perp_1w": {
      "exchange": "Bybit",
      "symbol": "CROUSDT",
      "market": "perp",
      "interval": "1w",
      "price": 0.10576,
      "signal_type": "bearish",
      "timestamp": "2025-06-15T02:31:42.569394+00:00"
    },
    "Bybit_OLUSDT_perp_1M": {
      "exchange": "Bybit",
      "symbol": "OLUSDT",
      "market": "perp",
      "interval": "1M",
      "price": 0.06179,
      "signal_type": "bearish",
      "timestamp": "2025-06-15T02:31:43.448418+00:00"
    },
    "Bybit_AVAILUSDT_perp_1d": {
      "exchange": "Bybit",
      "symbol": "AVAILUSDT",
      "market": "perp",
      "interval": "1d",
      "price": 0.03006,
      "signal_type": "bullish",
      "timestamp": "2025-06-15T02:31:44.445342+00:00"
    },
    "Bybit_SPECUSDT_perp_1M": {
      "exchange": "Bybit",
      "symbol": "SPECUSDT",
      "market": "perp",
      "interval": "1M",
      "price": 2.38,
      "signal_type": "bearish",
      "timestamp": "2025-06-15T02:31:45.442368+00:00"
    },
    "Bybit_RSS3USDT_perp_1M": {
      "exchange": "Bybit",
      "symbol": "RSS3USDT",
      "market": "perp",
      "interval": "1M",
      "price": 0.05887,
      "signal_type": "bearish",
      "timestamp": "2025-06-15T02:31:46.415482+00:00"
    },
    "Bybit_LOOKSUSDT_perp_1M": {
      "exchange": "Bybit",
      "symbol": "LOOKSUSDT",
      "market": "perp",
      "interval": "1M",
      "price": 0.02337,
      "signal_type": "bearish",
      "timestamp": "2025-06-15T02:31:47.426243+00:00"
    },
    "Bybit_10000SATSUSDT_perp_1d": {
      "exchange": "Bybit",
      "symbol": "10000SATSUSDT",
      "market": "perp",
      "interval": "1d",
      "price": 0.0004093,
      "signal_type": "bullish",
      "timestamp": "2025-06-15T02:31:48.432417+00:00"
    },
    "Bybit_COOKUSDT_perp_1d": {
      "exchange": "Bybit",
      "symbol": "COOKUSDT",
      "market": "perp",
      "interval": "1d",
      "price": 0.008298,
      "signal_type": "bullish",
      "timestamp": "2025-06-15T02:31:49.312986+00:00"
    },
    "Bybit_PRAIUSDT_perp_1d": {
      "exchange": "Bybit",
      "symbol": "PRAIUSDT",
      "market": "perp",
      "interval": "1d",
      "price": 0.02694,
      "signal_type": "bearish",
      "timestamp": "2025-06-15T02:31:50.295524+00:00"
    },
    "Bybit_CLOUDUSDT_perp_1M": {
      "exchange": "Bybit",
      "symbol": "CLOUDUSDT",
      "market": "perp",
      "interval": "1M",
      "price": 0.07383,
      "signal_type": "bullish",
      "timestamp": "2025-06-15T02:31:51.273316+00:00"
    },
    "Bybit_OLUSDT_perp_1d": {
      "exchange": "Bybit",
      "symbol": "OLUSDT",
      "market": "perp",
      "interval": "1d",
      "price": 0.03416,
      "signal_type": "bearish",
      "timestamp": "2025-06-15T02:31:52.280626+00:00"
    },
    "Bybit_SNTUSDT_perp_1M": {
      "exchange": "Bybit",
      "symbol": "SNTUSDT",
      "market": "perp",
      "interval": "1M",
      "price": 0.02253,
      "signal_type": "bullish",
      "timestamp": "2025-06-15T02:31:53.344853+00:00"
    },
    "Bybit_SPECUSDT_perp_1d": {
      "exchange": "Bybit",
      "symbol": "SPECUSDT",
      "market": "perp",
      "interval": "1d",
      "price": 0.884,
      "signal_type": "bearish",
      "timestamp": "2025-06-15T02:31:54.325849+00:00"
    },
    "Bybit_RSS3USDT_perp_1d": {
      "exchange": "Bybit",
      "symbol": "RSS3USDT",
      "market": "perp",
      "interval": "1d",
      "price": 0.04683,
      "signal_type": "bearish",
      "timestamp": "2025-06-15T02:31:55.200265+00:00"
    },
    "Bybit_DUCKUSDT_perp_1d": {
      "exchange": "Bybit",
      "symbol": "DUCKUSDT",
      "market": "perp",
      "interval": "1d",
      "price": 0.002562,
      "signal_type": "bullish",
      "timestamp": "2025-06-15T02:31:56.536060+00:00"
    },
    "Bybit_1000TOSHIUSDT_perp_1d": {
      "exchange": "Bybit",
      "symbol": "1000TOSHIUSDT",
      "market": "perp",
      "interval": "1d",
      "price": 0.5379,
      "signal_type": "bearish",
      "timestamp": "2025-06-15T02:31:57.438831+00:00"
    },
    "Bybit_SCAUSDT_perp_1M": {
      "exchange": "Bybit",
      "symbol": "SCAUSDT",
      "market": "perp",
      "interval": "1M",
      "price": 0.16081,
      "signal_type": "bearish",
      "timestamp": "2025-06-15T02:31:58.445159+00:00"
    },
    "Bybit_A8USDT_perp_1M": {
      "exchange": "Bybit",
      "symbol": "A8USDT",
      "market": "perp",
      "interval": "1M",
      "price": 0.13111,
      "signal_type": "bearish",
      "timestamp": "2025-06-15T02:31:59.304328+00:00"
    },
    "Bybit_10000COQUSDT_perp_1d": {
      "exchange": "Bybit",
      "symbol": "10000COQUSDT",
      "market": "perp",
      "interval": "1d",
      "price": 0.005988,
      "signal_type": "bearish",
      "timestamp": "2025-06-15T02:32:00.312091+00:00"
    },
    "Bybit_MOBILEUSDT_perp_1M": {
      "exchange": "Bybit",
      "symbol": "MOBILEUSDT",
      "market": "perp",
      "interval": "1M",
      "price": 0.0004908,
      "signal_type": "bearish",
      "timestamp": "2025-06-15T02:32:01.285585+00:00"
    },
    "Bybit_DBRUSDT_perp_1d": {
      "exchange": "Bybit",
      "symbol": "DBRUSDT",
      "market": "perp",
      "interval": "1d",
      "price": 0.01354,
      "signal_type": "bullish",
      "timestamp": "2025-06-15T02:32:02.262642+00:00"
    },
    "Bybit_BEAMUSDT_perp_1M": {
      "exchange": "Bybit",
      "symbol": "BEAMUSDT",
      "market": "perp",
      "interval": "1M",
      "price": 0.007212,
      "signal_type": "bearish",
      "timestamp": "2025-06-15T02:32:03.209457+00:00"
    },
    "Bybit_REXUSDT_perp_1M": {
      "exchange": "Bybit",
      "symbol": "REXUSDT",
      "market": "perp",
      "interval": "1M",
      "price": 0.03346,
      "signal_type": "bearish",
      "timestamp": "2025-06-15T02:32:04.196112+00:00"
    },
    "Bybit_ORBSUSDT_perp_1d": {
      "exchange": "Bybit",
      "symbol": "ORBSUSDT",
      "market": "perp",
      "interval": "1d",
      "price": 0.02373,
      "signal_type": "bearish",
      "timestamp": "2025-06-15T02:32:05.411644+00:00"
    },
    "Bybit_ALEOUSDT_perp_1M": {
      "exchange": "Bybit",
      "symbol": "ALEOUSDT",
      "market": "perp",
      "interval": "1M",
      "price": 0.2609,
      "signal_type": "bearish",
      "timestamp": "2025-06-15T02:32:06.613828+00:00"
    },
    "Bybit_COREUSDT_perp_1M": {
      "exchange": "Bybit",
      "symbol": "COREUSDT",
      "market": "perp",
      "interval": "1M",
      "price": 0.7874,
      "signal_type": "bearish",
      "timestamp": "2025-06-15T02:32:07.576684+00:00"
    },
    "Bybit_JUSDT_perp_1M": {
      "exchange": "Bybit",
      "symbol": "JUSDT",
      "market": "perp",
      "interval": "1M",
      "price": 0.2258,
      "signal_type": "bearish",
      "timestamp": "2025-06-15T02:32:08.791400+00:00"
    },
    "Bybit_OBTUSDT_perp_1d": {
      "exchange": "Bybit",
      "symbol": "OBTUSDT",
      "market": "perp",
      "interval": "1d",
      "price": 0.00747,
      "signal_type": "bullish",
      "timestamp": "2025-06-15T02:32:09.814773+00:00"
    },
    "Bybit_10000LADYSUSDT_perp_1d": {
      "exchange": "Bybit",
      "symbol": "10000LADYSUSDT",
      "market": "perp",
      "interval": "1d",
      "price": 0.0004135,
      "signal_type": "bullish",
      "timestamp": "2025-06-15T02:32:10.804439+00:00"
    },
    "Bybit_GODSUSDT_perp_1d": {
      "exchange": "Bybit",
      "symbol": "GODSUSDT",
      "market": "perp",
      "interval": "1d",
      "price": 0.1283,
      "signal_type": "bullish",
      "timestamp": "2025-06-15T02:32:11.696963+00:00"
    },
    "Bybit_A8USDT_perp_1d": {
      "exchange": "Bybit",
      "symbol": "A8USDT",
      "market": "perp",
      "interval": "1d",
      "price": 0.11513,
      "signal_type": "bearish",
      "timestamp": "2025-06-15T02:32:12.681273+00:00"
    },
    "Bybit_RAYDIUMUSDT_perp_1M": {
      "exchange": "Bybit",
      "symbol": "RAYDIUMUSDT",
      "market": "perp",
      "interval": "1M",
      "price": 2.7924,
      "signal_type": "bearish",
      "timestamp": "2025-06-15T02:32:13.591088+00:00"
    },
    "Bybit_MASAUSDT_perp_1M": {
      "exchange": "Bybit",
      "symbol": "MASAUSDT",
      "market": "perp",
      "interval": "1M",
      "price": 0.02862,
      "signal_type": "bearish",
      "timestamp": "2025-06-15T02:32:14.559775+00:00"
    },
    "Bybit_FUSDT_perp_1d": {
      "exchange": "Bybit",
      "symbol": "FUSDT",
      "market": "perp",
      "interval": "1d",
      "price": 0.01009,
      "signal_type": "bullish",
      "timestamp": "2025-06-15T02:32:15.473676+00:00"
    },
    "Bybit_MOBILEUSDT_perp_1d": {
      "exchange": "Bybit",
      "symbol": "MOBILEUSDT",
      "market": "perp",
      "interval": "1d",
      "price": 0.0003039,
      "signal_type": "bullish",
      "timestamp": "2025-06-15T02:32:16.465734+00:00"
    },
    "Bybit_PEAQUSDT_perp_1M": {
      "exchange": "Bybit",
      "symbol": "PEAQUSDT",
      "market": "perp",
      "interval": "1M",
      "price": 0.1283,
      "signal_type": "bearish",
      "timestamp": "2025-06-15T02:32:17.424233+00:00"
    },
    "Bybit_ORDERUSDT_perp_1M": {
      "exchange": "Bybit",
      "symbol": "ORDERUSDT",
      "market": "perp",
      "interval": "1M",
      "price": 0.1043,
      "signal_type": "bearish",
      "timestamp": "2025-06-15T02:32:18.406109+00:00"
    },
    "Bybit_JUSDT_perp_1d": {
      "exchange": "Bybit",
      "symbol": "JUSDT",
      "market": "perp",
      "interval": "1d",
      "price": 0.1625,
      "signal_type": "bearish",
      "timestamp": "2025-06-15T02:32:19.282766+00:00"
    },
    "Bybit_SOLAYERUSDT_perp_1M": {
      "exchange": "Bybit",
      "symbol": "SOLAYERUSDT",
      "market": "perp",
      "interval": "1M",
      "price": 3.0407,
      "signal_type": "bearish",
      "timestamp": "2025-06-15T02:32:20.255622+00:00"
    },
    "Bybit_SENDUSDT_perp_1M": {
      "exchange": "Bybit",
      "symbol": "SENDUSDT",
      "market": "perp",
      "interval": "1M",
      "price": 0.7839,
      "signal_type": "bearish",
      "timestamp": "2025-06-15T02:32:21.223985+00:00"
    },
    "Bybit_CARVUSDT_perp_1M": {
      "exchange": "Bybit",
      "symbol": "CARVUSDT",
      "market": "perp",
      "interval": "1M",
      "price": 0.3794,
      "signal_type": "bearish",
      "timestamp": "2025-06-15T02:32:22.204818+00:00"
    },
    "Bybit_1000APUUSDT_perp_1d": {
      "exchange": "Bybit",
      "symbol": "1000APUUSDT",
      "market": "perp",
      "interval": "1d",
      "price": 0.1998,
      "signal_type": "bearish",
      "timestamp": "2025-06-15T02:32:23.109217+00:00"
    },
    "Bybit_MVLUSDT_perp_1M": {
      "exchange": "Bybit",
      "symbol": "MVLUSDT",
      "market": "perp",
      "interval": "1M",
      "price": 0.003522,
      "signal_type": "bearish",
      "timestamp": "2025-06-15T02:32:24.105487+00:00"
    },
    "Bybit_SENDUSDT_perp_1w": {
      "exchange": "Bybit",
      "symbol": "SENDUSDT",
      "market": "perp",
      "interval": "1w",
      "price": 0.724,
      "signal_type": "bearish",
      "timestamp": "2025-06-15T02:32:25.066055+00:00"
    },
    "Bybit_SOLOUSDT_perp_1M": {
      "exchange": "Bybit",
      "symbol": "SOLOUSDT",
      "market": "perp",
      "interval": "1M",
      "price": 0.2001,
      "signal_type": "bullish",
      "timestamp": "2025-06-15T02:32:26.095782+00:00"
    },
    "Bybit_LAUNCHCOINUSDT_perp_1w": {
      "exchange": "Bybit",
      "symbol": "LAUNCHCOINUSDT",
      "market": "perp",
      "interval": "1w",
      "price": 0.11937,
      "signal_type": "bullish",
      "timestamp": "2025-06-15T02:32:27.061135+00:00"
    },
    "Bybit_RFCUSDT_perp_1d": {
      "exchange": "Bybit",
      "symbol": "RFCUSDT",
      "market": "perp",
      "interval": "1d",
      "price": 0.0078,
      "signal_type": "bullish",
      "timestamp": "2025-06-15T02:32:28.073106+00:00"
    },
    "Bybit_HNTUSDT_perp_1M": {
      "exchange": "Bybit",
      "symbol": "HNTUSDT",
      "market": "perp",
      "interval": "1M",
      "price": 3.86,
      "signal_type": "bearish",
      "timestamp": "2025-06-15T02:32:28.971930+00:00"
    },
    "Bybit_BLASTUSDT_perp_1M": {
      "exchange": "Bybit",
      "symbol": "BLASTUSDT",
      "market": "perp",
      "interval": "1M",
      "price": 0.003546,
      "signal_type": "bearish",
      "timestamp": "2025-06-15T02:32:29.976947+00:00"
    },
    "Bybit_AGIUSDT_perp_1M": {
      "exchange": "Bybit",
      "symbol": "AGIUSDT",
      "market": "perp",
      "interval": "1M",
      "price": 0.06716,
      "signal_type": "bearish",
      "timestamp": "2025-06-15T02:32:30.848586+00:00"
    },
    "Bybit_FLOCKUSDT_perp_1d": {
      "exchange": "Bybit",
      "symbol": "FLOCKUSDT",
      "market": "perp",
      "interval": "1d",
      "price": 0.17432,
      "signal_type": "bearish",
      "timestamp": "2025-06-15T02:32:31.826791+00:00"
    },
    "Bybit_FLRUSDT_perp_1d": {
      "exchange": "Bybit",
      "symbol": "FLRUSDT",
      "market": "perp",
      "interval": "1d",
      "price": 0.01825,
      "signal_type": "bearish",
      "timestamp": "2025-06-15T02:32:32.800903+00:00"
    },
    "Bybit_ETHBTCUSDT_perp_1M": {
      "exchange": "Bybit",
      "symbol": "ETHBTCUSDT",
      "market": "perp",
      "interval": "1M",
      "price": 0.019055,
      "signal_type": "bullish",
      "timestamp": "2025-06-15T02:32:33.765776+00:00"
    },
    "Bybit_ROAMUSDT_perp_1M": {
      "exchange": "Bybit",
      "symbol": "ROAMUSDT",
      "market": "perp",
      "interval": "1M",
      "price": 0.2892,
      "signal_type": "bearish",
      "timestamp": "2025-06-15T02:32:34.742311+00:00"
    },
    "Bybit_HNTUSDT_perp_1d": {
      "exchange": "Bybit",
      "symbol": "HNTUSDT",
      "market": "perp",
      "interval": "1d",
      "price": 2.413,
      "signal_type": "bullish",
      "timestamp": "2025-06-15T02:32:35.725568+00:00"
    },
    "Bybit_AFCUSDT_spot_1M": {
      "exchange": "Bybit",
      "symbol": "AFCUSDT",
      "market": "spot",
      "interval": "1M",
      "price": 0.6078,
      "signal_type": "bearish",
      "timestamp": "2025-06-15T02:32:36.698001+00:00"
    },
    "Bybit_ZKLUSDT_spot_1M": {
      "exchange": "Bybit",
      "symbol": "ZKLUSDT",
      "market": "spot",
      "interval": "1M",
      "price": 0.06024,
      "signal_type": "bearish",
      "timestamp": "2025-06-15T02:32:37.665137+00:00"
    },
    "Bybit_TRVLUSDT_spot_1M": {
      "exchange": "Bybit",
      "symbol": "TRVLUSDT",
      "market": "spot",
      "interval": "1M",
      "price": 0.007511,
      "signal_type": "bullish",
      "timestamp": "2025-06-15T02:32:38.600772+00:00"
    },
    "Bybit_JEFFUSDT_spot_1M": {
      "exchange": "Bybit",
      "symbol": "JEFFUSDT",
      "market": "spot",
      "interval": "1M",
      "price": 0.005406,
      "signal_type": "bearish",
      "timestamp": "2025-06-15T02:32:39.566432+00:00"
    },
    "Bybit_SMILEUSDT_spot_1M": {
      "exchange": "Bybit",
      "symbol": "SMILEUSDT",
      "market": "spot",
      "interval": "1M",
      "price": 0.02559,
      "signal_type": "bearish",
      "timestamp": "2025-06-15T02:32:40.516933+00:00"
    },
    "Bybit_METHUSDT_spot_1M": {
      "exchange": "Bybit",
      "symbol": "METHUSDT",
      "market": "spot",
      "interval": "1M",
      "price": 1907.73,
      "signal_type": "bullish",
      "timestamp": "2025-06-15T02:32:41.483060+00:00"
    },
    "Bybit_HATUSDT_spot_1M": {
      "exchange": "Bybit",
      "symbol": "HATUSDT",
      "market": "spot",
      "interval": "1M",
      "price": 0.00509,
      "signal_type": "bearish",
      "timestamp": "2025-06-15T02:32:42.493638+00:00"
    },
    "Bybit_DARKUSDT_perp_1d": {
      "exchange": "Bybit",
      "symbol": "DARKUSDT",
      "market": "perp",
      "interval": "1d",
      "price": 0.005,
      "signal_type": "bullish",
      "timestamp": "2025-06-15T02:32:43.478057+00:00"
    },
    "Bybit_CAPSUSDT_spot_1d": {
      "exchange": "Bybit",
      "symbol": "CAPSUSDT",
      "market": "spot",
      "interval": "1d",
      "price": 0.001134,
      "signal_type": "bearish",
      "timestamp": "2025-06-15T02:32:44.415879+00:00"
    },
    "Bybit_FTNUSDT_perp_1d": {
      "exchange": "Bybit",
      "symbol": "FTNUSDT",
      "market": "perp",
      "interval": "1d",
      "price": 4.4491,
      "signal_type": "bearish",
      "timestamp": "2025-06-15T02:32:45.368058+00:00"
    },
    "Bybit_APRSUSDT_spot_1d": {
      "exchange": "Bybit",
      "symbol": "APRSUSDT",
      "market": "spot",
      "interval": "1d",
      "price": 0.005257,
      "signal_type": "bullish",
      "timestamp": "2025-06-15T02:32:46.343596+00:00"
    },
    "Bybit_SOSOUSDT_spot_1d": {
      "exchange": "Bybit",
      "symbol": "SOSOUSDT",
      "market": "spot",
      "interval": "1d",
      "price": 0.4516,
      "signal_type": "bullish",
      "timestamp": "2025-06-15T02:32:47.301711+00:00"
    },
    "Bybit_XUSDT_spot_1d": {
      "exchange": "Bybit",
      "symbol": "XUSDT",
      "market": "spot",
      "interval": "1d",
      "price": 5.884e-05,
      "signal_type": "bullish",
      "timestamp": "2025-06-15T02:32:48.168618+00:00"
    },
    "Bybit_BCUTUSDT_spot_1w": {
      "exchange": "Bybit",
      "symbol": "BCUTUSDT",
      "market": "spot",
      "interval": "1w",
      "price": 0.02067,
      "signal_type": "bullish",
      "timestamp": "2025-06-15T02:32:49.127078+00:00"
    },
    "Bybit_ELDEUSDT_spot_1w": {
      "exchange": "Bybit",
      "symbol": "ELDEUSDT",
      "market": "spot",
      "interval": "1w",
      "price": 0.10457,
      "signal_type": "bearish",
      "timestamp": "2025-06-15T02:32:50.140264+00:00"
    },
    "Bybit_LMWRUSDT_spot_1M": {
      "exchange": "Bybit",
      "symbol": "LMWRUSDT",
      "market": "spot",
      "interval": "1M",
      "price": 0.09688,
      "signal_type": "bearish",
      "timestamp": "2025-06-15T02:32:51.116843+00:00"
    },
    "Bybit_MEEUSDT_spot_1M": {
      "exchange": "Bybit",
      "symbol": "MEEUSDT",
      "market": "spot",
      "interval": "1M",
      "price": 0.003701,
      "signal_type": "bearish",
      "timestamp": "2025-06-15T02:32:52.409746+00:00"
    },
    "Bybit_XEMUSDT_spot_1M": {
      "exchange": "Bybit",
      "symbol": "XEMUSDT",
      "market": "spot",
      "interval": "1M",
      "price": 0.01984,
      "signal_type": "bearish",
      "timestamp": "2025-06-15T02:32:53.385257+00:00"
    },
    "Bybit_PYUSDUSDT_spot_1d": {
      "exchange": "Bybit",
      "symbol": "PYUSDUSDT",
      "market": "spot",
      "interval": "1d",
      "price": 1.0002,
      "signal_type": "bearish",
      "timestamp": "2025-06-15T02:32:54.256133+00:00"
    },
    "Bybit_PFVSUSDT_spot_1w": {
      "exchange": "Bybit",
      "symbol": "PFVSUSDT",
      "market": "spot",
      "interval": "1w",
      "price": 0.03478,
      "signal_type": "bearish",
      "timestamp": "2025-06-15T02:32:55.274201+00:00"
    },
    "Bybit_DMAILUSDT_spot_1w": {
      "exchange": "Bybit",
      "symbol": "DMAILUSDT",
      "market": "spot",
      "interval": "1w",
      "price": 0.166,
      "signal_type": "bearish",
      "timestamp": "2025-06-15T02:32:56.139425+00:00"
    },
    "Bybit_INTERUSDT_spot_1M": {
      "exchange": "Bybit",
      "symbol": "INTERUSDT",
      "market": "spot",
      "interval": "1M",
      "price": 0.874,
      "signal_type": "bearish",
      "timestamp": "2025-06-15T02:32:57.114654+00:00"
    },
    "Bybit_GALAXISUSDT_spot_1w": {
      "exchange": "Bybit",
      "symbol": "GALAXISUSDT",
      "market": "spot",
      "interval": "1w",
      "price": 0.0004147,
      "signal_type": "bearish",
      "timestamp": "2025-06-15T02:32:58.339209+00:00"
    },
    "Bybit_LADYSUSDT_spot_1d": {
      "exchange": "Bybit",
      "symbol": "LADYSUSDT",
      "market": "spot",
      "interval": "1d",
      "price": 4.135e-08,
      "signal_type": "bullish",
      "timestamp": "2025-06-15T02:32:59.324572+00:00"
    },
    "Bybit_FMCUSDT_spot_1d": {
      "exchange": "Bybit",
      "symbol": "FMCUSDT",
      "market": "spot",
      "interval": "1d",
      "price": 0.0004282,
      "signal_type": "bullish",
      "timestamp": "2025-06-15T02:33:00.268575+00:00"
    },
    "Bybit_AGLAUSDT_spot_1d": {
      "exchange": "Bybit",
      "symbol": "AGLAUSDT",
      "market": "spot",
      "interval": "1d",
      "price": 0.0010762,
      "signal_type": "bullish",
      "timestamp": "2025-06-15T02:33:01.225092+00:00"
    },
    "Bybit_MPLXUSDT_spot_1M": {
      "exchange": "Bybit",
      "symbol": "MPLXUSDT",
      "market": "spot",
      "interval": "1M",
      "price": 0.19864,
      "signal_type": "bearish",
      "timestamp": "2025-06-15T02:33:02.087225+00:00"
    },
    "Bybit_OIKUSDT_spot_1M": {
      "exchange": "Bybit",
      "symbol": "OIKUSDT",
      "market": "spot",
      "interval": "1M",
      "price": 0.01855,
      "signal_type": "bullish",
      "timestamp": "2025-06-15T02:33:03.039840+00:00"
    },
    "Bybit_VINUUSDT_spot_1d": {
      "exchange": "Bybit",
      "symbol": "VINUUSDT",
      "market": "spot",
      "interval": "1d",
      "price": 1.8855e-08,
      "signal_type": "bullish",
      "timestamp": "2025-06-15T02:33:03.987837+00:00"
    },
    "Bybit_LLUSDT_spot_1M": {
      "exchange": "Bybit",
      "symbol": "LLUSDT",
      "market": "spot",
      "interval": "1M",
      "price": 0.01223,
      "signal_type": "bullish",
      "timestamp": "2025-06-15T02:33:04.946018+00:00"
    },
    "Bybit_OMGUSDT_spot_1d": {
      "exchange": "Bybit",
      "symbol": "OMGUSDT",
      "market": "spot",
      "interval": "1d",
      "price": 0.1786,
      "signal_type": "bullish",
      "timestamp": "2025-06-15T02:33:05.817586+00:00"
    },
    "Bybit_COQUSDT_spot_1d": {
      "exchange": "Bybit",
      "symbol": "COQUSDT",
      "market": "spot",
      "interval": "1d",
      "price": 5.99e-07,
      "signal_type": "bearish",
      "timestamp": "2025-06-15T02:33:06.798302+00:00"
    },
    "Bybit_APPUSDT_spot_1d": {
      "exchange": "Bybit",
      "symbol": "APPUSDT",
      "market": "spot",
      "interval": "1d",
      "price": 0.006847,
      "signal_type": "bullish",
      "timestamp": "2025-06-15T02:33:07.656543+00:00"
    },
    "Bybit_MPLXUSDT_spot_1d": {
      "exchange": "Bybit",
      "symbol": "MPLXUSDT",
      "market": "spot",
      "interval": "1d",
      "price": 0.13112,
      "signal_type": "bearish",
      "timestamp": "2025-06-15T02:33:08.628218+00:00"
    },
    "Bybit_NLKUSDT_spot_1M": {
      "exchange": "Bybit",
      "symbol": "NLKUSDT",
      "market": "spot",
      "interval": "1M",
      "price": 0.003021,
      "signal_type": "bullish",
      "timestamp": "2025-06-15T02:33:09.580403+00:00"
    },
    "Bybit_ESEUSDT_spot_1M": {
      "exchange": "Bybit",
      "symbol": "ESEUSDT",
      "market": "spot",
      "interval": "1M",
      "price": 0.010258,
      "signal_type": "bearish",
      "timestamp": "2025-06-15T02:33:10.770148+00:00"
    },
    "Bybit_XARUSDT_spot_1M": {
      "exchange": "Bybit",
      "symbol": "XARUSDT",
      "market": "spot",
      "interval": "1M",
      "price": 0.007314,
      "signal_type": "bearish",
      "timestamp": "2025-06-15T02:33:11.711294+00:00"
    },
    "Bybit_WAVESUSDT_spot_1d": {
      "exchange": "Bybit",
      "symbol": "WAVESUSDT",
      "market": "spot",
      "interval": "1d",
      "price": 1.056,
      "signal_type": "bearish",
      "timestamp": "2025-06-15T02:33:12.686298+00:00"
    },
    "Bybit_FARUSDT_spot_1d": {
      "exchange": "Bybit",
      "symbol": "FARUSDT",
      "market": "spot",
      "interval": "1d",
      "price": 0.000598,
      "signal_type": "bearish",
      "timestamp": "2025-06-15T02:33:13.559643+00:00"
    },
    "Bybit_LUNAIUSDT_spot_1w": {
      "exchange": "Bybit",
      "symbol": "LUNAIUSDT",
      "market": "spot",
      "interval": "1w",
      "price": 0.02456,
      "signal_type": "bearish",
      "timestamp": "2025-06-15T02:33:14.609020+00:00"
    },
    "Bybit_GALFTUSDT_spot_1M": {
      "exchange": "Bybit",
      "symbol": "GALFTUSDT",
      "market": "spot",
      "interval": "1M",
      "price": 2.936,
      "signal_type": "bearish",
      "timestamp": "2025-06-15T02:33:15.484050+00:00"
    },
    "Bybit_NLKUSDT_spot_1w": {
      "exchange": "Bybit",
      "symbol": "NLKUSDT",
      "market": "spot",
      "interval": "1w",
      "price": 0.003343,
      "signal_type": "bullish",
      "timestamp": "2025-06-15T02:33:16.453053+00:00"
    },
    "Bybit_DOMEUSDT_spot_1d": {
      "exchange": "Bybit",
      "symbol": "DOMEUSDT",
      "market": "spot",
      "interval": "1d",
      "price": 0.000255,
      "signal_type": "bearish",
      "timestamp": "2025-06-15T02:33:17.441240+00:00"
    },
    "Bybit_STREAMUSDT_spot_1M": {
      "exchange": "Bybit",
      "symbol": "STREAMUSDT",
      "market": "spot",
      "interval": "1M",
      "price": 0.01769,
      "signal_type": "bullish",
      "timestamp": "2025-06-15T02:33:18.409648+00:00"
    },
    "Bybit_LUNAIUSDT_spot_1d": {
      "exchange": "Bybit",
      "symbol": "LUNAIUSDT",
      "market": "spot",
      "interval": "1d",
      "price": 0.01907,
      "signal_type": "bearish",
      "timestamp": "2025-06-15T02:33:19.802348+00:00"
    },
    "Bybit_GAMEUSDT_spot_1M": {
      "exchange": "Bybit",
      "symbol": "GAMEUSDT",
      "market": "spot",
      "interval": "1M",
      "price": 0.05715,
      "signal_type": "bearish",
      "timestamp": "2025-06-15T02:33:21.014327+00:00"
    },
    "Bybit_5IREUSDT_spot_1w": {
      "exchange": "Bybit",
      "symbol": "5IREUSDT",
      "market": "spot",
      "interval": "1w",
      "price": 0.001786,
      "signal_type": "bearish",
      "timestamp": "2025-06-15T02:33:21.873389+00:00"
    },
    "Bybit_EXVGUSDT_spot_1M": {
      "exchange": "Bybit",
      "symbol": "EXVGUSDT",
      "market": "spot",
      "interval": "1M",
      "price": 0.006511,
      "signal_type": "bearish",
      "timestamp": "2025-06-15T02:33:22.890602+00:00"
    },
    "Bybit_ZENTUSDT_spot_1d": {
      "exchange": "Bybit",
      "symbol": "ZENTUSDT",
      "market": "spot",
      "interval": "1d",
      "price": 0.00774,
      "signal_type": "bullish",
      "timestamp": "2025-06-15T02:33:23.777593+00:00"
    },
    "Bybit_BTC3LUSDT_spot_1d": {
      "exchange": "Bybit",
      "symbol": "BTC3LUSDT",
      "market": "spot",
      "interval": "1d",
      "price": 6.6426,
      "signal_type": "bearish",
      "timestamp": "2025-06-15T02:33:24.759505+00:00"
    },
    "Bybit_TELUSDT_spot_1M": {
      "exchange": "Bybit",
      "symbol": "TELUSDT",
      "market": "spot",
      "interval": "1M",
      "price": 0.005239,
      "signal_type": "bearish",
      "timestamp": "2025-06-15T02:33:25.667536+00:00"
    },
    "Bybit_MNRYUSDT_spot_1d": {
      "exchange": "Bybit",
      "symbol": "MNRYUSDT",
      "market": "spot",
      "interval": "1d",
      "price": 0.01048,
      "signal_type": "bearish",
      "timestamp": "2025-06-15T02:33:26.646454+00:00"
    },
    "Bybit_MDAOUSDT_spot_1M": {
      "exchange": "Bybit",
      "symbol": "MDAOUSDT",
      "market": "spot",
      "interval": "1M",
      "price": 0.02299,
      "signal_type": "bullish",
      "timestamp": "2025-06-15T02:33:27.561037+00:00"
    },
    "Bybit_CMETHUSDT_spot_1M": {
      "exchange": "Bybit",
      "symbol": "CMETHUSDT",
      "market": "spot",
      "interval": "1M",
      "price": 1908.38,
      "signal_type": "bullish",
      "timestamp": "2025-06-15T02:33:28.806749+00:00"
    },
    "Bybit_SHRAPUSDT_spot_1d": {
      "exchange": "Bybit",
      "symbol": "SHRAPUSDT",
      "market": "spot",
      "interval": "1d",
      "price": 0.00453,
      "signal_type": "bearish",
      "timestamp": "2025-06-15T02:33:29.744363+00:00"
    },
    "Bybit_AARKUSDT_spot_1M": {
      "exchange": "Bybit",
      "symbol": "AARKUSDT",
      "market": "spot",
      "interval": "1M",
      "price": 0.001653,
      "signal_type": "bullish",
      "timestamp": "2025-06-15T02:33:30.726634+00:00"
    },
    "Bybit_GAMEUSDT_spot_1d": {
      "exchange": "Bybit",
      "symbol": "GAMEUSDT",
      "market": "spot",
      "interval": "1d",
      "price": 0.03523,
      "signal_type": "bullish",
      "timestamp": "2025-06-15T02:33:31.609659+00:00"
    },
    "Bybit_VPRUSDT_spot_1M": {
      "exchange": "Bybit",
      "symbol": "VPRUSDT",
      "market": "spot",
      "interval": "1M",
      "price": 0.0005267,
      "signal_type": "bullish",
      "timestamp": "2025-06-15T02:33:32.578638+00:00"
    },
    "Bybit_BABY1USDT_spot_1M": {
      "exchange": "Bybit",
      "symbol": "BABY1USDT",
      "market": "spot",
      "interval": "1M",
      "price": 0.10541,
      "signal_type": "bearish",
      "timestamp": "2025-06-15T02:33:33.431118+00:00"
    },
    "Bybit_LAVAUSDT_spot_1d": {
      "exchange": "Bybit",
      "symbol": "LAVAUSDT",
      "market": "spot",
      "interval": "1d",
      "price": 0.068,
      "signal_type": "bearish",
      "timestamp": "2025-06-15T02:33:34.411478+00:00"
    },
    "Bybit_ARTYUSDT_spot_1d": {
      "exchange": "Bybit",
      "symbol": "ARTYUSDT",
      "market": "spot",
      "interval": "1d",
      "price": 0.1565,
      "signal_type": "bullish",
      "timestamp": "2025-06-15T02:33:35.353689+00:00"
    },
    "Bybit_APEXUSDT_spot_1M": {
      "exchange": "Bybit",
      "symbol": "APEXUSDT",
      "market": "spot",
      "interval": "1M",
      "price": 0.8249,
      "signal_type": "bearish",
      "timestamp": "2025-06-15T02:33:36.324717+00:00"
    },
    "Bybit_MDAOUSDT_spot_1d": {
      "exchange": "Bybit",
      "symbol": "MDAOUSDT",
      "market": "spot",
      "interval": "1d",
      "price": 0.02394,
      "signal_type": "bullish",
      "timestamp": "2025-06-15T02:33:37.269401+00:00"
    },
    "Bybit_ROOTUSDT_spot_1w": {
      "exchange": "Bybit",
      "symbol": "ROOTUSDT",
      "market": "spot",
      "interval": "1w",
      "price": 0.003871,
      "signal_type": "bullish",
      "timestamp": "2025-06-15T02:33:38.302598+00:00"
    },
    "Bybit_RPKUSDT_spot_1M": {
      "exchange": "Bybit",
      "symbol": "RPKUSDT",
      "market": "spot",
      "interval": "1M",
      "price": 0.001223,
      "signal_type": "bullish",
      "timestamp": "2025-06-15T02:33:39.200235+00:00"
    },
    "Bybit_MVUSDT_spot_1d": {
      "exchange": "Bybit",
      "symbol": "MVUSDT",
      "market": "spot",
      "interval": "1d",
      "price": 0.006014,
      "signal_type": "bullish",
      "timestamp": "2025-06-15T02:33:40.191626+00:00"
    },
    "Bybit_DUELUSDT_spot_1M": {
      "exchange": "Bybit",
      "symbol": "DUELUSDT",
      "market": "spot",
      "interval": "1M",
      "price": 0.0010204,
      "signal_type": "bearish",
      "timestamp": "2025-06-15T02:33:41.106823+00:00"
    },
    "Bybit_SVLUSDT_spot_1d": {
      "exchange": "Bybit",
      "symbol": "SVLUSDT",
      "market": "spot",
      "interval": "1d",
      "price": 0.006173,
      "signal_type": "bearish",
      "timestamp": "2025-06-15T02:33:42.072258+00:00"
    },
    "Bybit_IZIUSDT_spot_1d": {
      "exchange": "Bybit",
      "symbol": "IZIUSDT",
      "market": "spot",
      "interval": "1d",
      "price": 0.004502,
      "signal_type": "bullish",
      "timestamp": "2025-06-15T02:33:42.982962+00:00"
    },
    "Bybit_EGP1USDT_spot_1M": {
      "exchange": "Bybit",
      "symbol": "EGP1USDT",
      "market": "spot",
      "interval": "1M",
      "price": 0.8467,
      "signal_type": "bullish",
      "timestamp": "2025-06-15T02:33:43.987077+00:00"
    },
    "Bybit_ROOTUSDT_spot_1d": {
      "exchange": "Bybit",
      "symbol": "ROOTUSDT",
      "market": "spot",
      "interval": "1d",
      "price": 0.005285,
      "signal_type": "bearish",
      "timestamp": "2025-06-15T02:33:44.907551+00:00"
    },
    "Bybit_VPRUSDT_spot_1d": {
      "exchange": "Bybit",
      "symbol": "VPRUSDT",
      "market": "spot",
      "interval": "1d",
      "price": 0.0005617,
      "signal_type": "bullish",
      "timestamp": "2025-06-15T02:33:45.864204+00:00"
    },
    "Bybit_G7USDT_spot_1M": {
      "exchange": "Bybit",
      "symbol": "G7USDT",
      "market": "spot",
      "interval": "1M",
      "price": 0.005231,
      "signal_type": "bearish",
      "timestamp": "2025-06-15T02:33:46.737691+00:00"
    },
    "Bybit_ZORAUSDT_spot_1M": {
      "exchange": "Bybit",
      "symbol": "ZORAUSDT",
      "market": "spot",
      "interval": "1M",
      "price": 0.01335,
      "signal_type": "bearish",
      "timestamp": "2025-06-15T02:33:47.706423+00:00"
    },
    "Bybit_BTC3SUSDT_spot_1d": {
      "exchange": "Bybit",
      "symbol": "BTC3SUSDT",
      "market": "spot",
      "interval": "1d",
      "price": 0.00819,
      "signal_type": "bullish",
      "timestamp": "2025-06-15T02:33:48.577206+00:00"
    },
    "Bybit_ERTHAUSDT_spot_1M": {
      "exchange": "Bybit",
      "symbol": "ERTHAUSDT",
      "market": "spot",
      "interval": "1M",
      "price": 0.0004937,
      "signal_type": "bullish",
      "timestamp": "2025-06-15T02:33:49.567407+00:00"
    },
    "Bybit_ELIXUSDT_spot_1M": {
      "exchange": "Bybit",
      "symbol": "ELIXUSDT",
      "market": "spot",
      "interval": "1M",
      "price": 0.006347,
      "signal_type": "bearish",
      "timestamp": "2025-06-15T02:33:50.462954+00:00"
    },
    "Bybit_XIONUSDT_spot_1w": {
      "exchange": "Bybit",
      "symbol": "XIONUSDT",
      "market": "spot",
      "interval": "1w",
      "price": 0.9401,
      "signal_type": "bullish",
      "timestamp": "2025-06-15T02:33:51.442077+00:00"
    },
    "Bybit_ZEXUSDT_spot_1d": {
      "exchange": "Bybit",
      "symbol": "ZEXUSDT",
      "market": "spot",
      "interval": "1d",
      "price": 0.1385,
      "signal_type": "bearish",
      "timestamp": "2025-06-15T02:33:52.313312+00:00"
    },
    "Bybit_EVERUSDT_spot_1w": {
      "exchange": "Bybit",
      "symbol": "EVERUSDT",
      "market": "spot",
      "interval": "1w",
      "price": 0.010107,
      "signal_type": "bullish",
      "timestamp": "2025-06-15T02:33:53.331228+00:00"
    },
    "Bybit_EGP1USDT_spot_1d": {
      "exchange": "Bybit",
      "symbol": "EGP1USDT",
      "market": "spot",
      "interval": "1d",
      "price": 0.9803,
      "signal_type": "bullish",
      "timestamp": "2025-06-15T02:33:54.213936+00:00"
    },
    "Bybit_G7USDT_spot_1d": {
      "exchange": "Bybit",
      "symbol": "G7USDT",
      "market": "spot",
      "interval": "1d",
      "price": 0.004478,
      "signal_type": "bullish",
      "timestamp": "2025-06-15T02:33:55.199652+00:00"
    },
    "Bybit_ZORAUSDT_spot_1d": {
      "exchange": "Bybit",
      "symbol": "ZORAUSDT",
      "market": "spot",
      "interval": "1d",
      "price": 0.00872,
      "signal_type": "bullish",
      "timestamp": "2025-06-15T02:33:56.113042+00:00"
    },
    "Bybit_SQTUSDT_spot_1d": {
      "exchange": "Bybit",
      "symbol": "SQTUSDT",
      "market": "spot",
      "interval": "1d",
      "price": 0.001117,
      "signal_type": "bullish",
      "timestamp": "2025-06-15T02:33:57.082513+00:00"
    },
    "Bybit_FORTUSDT_spot_1w": {
      "exchange": "Bybit",
      "symbol": "FORTUSDT",
      "market": "spot",
      "interval": "1w",
      "price": 0.08203,
      "signal_type": "bearish",
      "timestamp": "2025-06-15T02:33:57.945636+00:00"
    },
    "Bybit_MODEUSDT_spot_1M": {
      "exchange": "Bybit",
      "symbol": "MODEUSDT",
      "market": "spot",
      "interval": "1M",
      "price": 0.005038,
      "signal_type": "bearish",
      "timestamp": "2025-06-15T02:33:58.926289+00:00"
    },
    "Bybit_BBQUSDT_spot_1d": {
      "exchange": "Bybit",
      "symbol": "BBQUSDT",
      "market": "spot",
      "interval": "1d",
      "price": 0.01547,
      "signal_type": "bearish",
      "timestamp": "2025-06-15T02:33:59.825579+00:00"
    },
    "Bybit_ERTHAUSDT_spot_1d": {
      "exchange": "Bybit",
      "symbol": "ERTHAUSDT",
      "market": "spot",
      "interval": "1d",
      "price": 0.0005643,
      "signal_type": "bullish",
      "timestamp": "2025-06-15T02:34:01.080378+00:00"
    },
    "Bybit_ZTXUSDT_spot_1d": {
      "exchange": "Bybit",
      "symbol": "ZTXUSDT",
      "market": "spot",
      "interval": "1d",
      "price": 0.002364,
      "signal_type": "bullish",
      "timestamp": "2025-06-15T02:34:02.180858+00:00"
    },
    "Bybit_SISUSDT_spot_1M": {
      "exchange": "Bybit",
      "symbol": "SISUSDT",
      "market": "spot",
      "interval": "1M",
      "price": 0.04912,
      "signal_type": "bullish",
      "timestamp": "2025-06-15T02:34:03.151084+00:00"
    },
    "Bybit_ELIXUSDT_spot_1d": {
      "exchange": "Bybit",
      "symbol": "ELIXUSDT",
      "market": "spot",
      "interval": "1d",
      "price": 0.004203,
      "signal_type": "bearish",
      "timestamp": "2025-06-15T02:34:04.084827+00:00"
    },
    "Bybit_AURORAUSDT_spot_1M": {
      "exchange": "Bybit",
      "symbol": "AURORAUSDT",
      "market": "spot",
      "interval": "1M",
      "price": 0.09316,
      "signal_type": "bearish",
      "timestamp": "2025-06-15T02:34:05.070240+00:00"
    },
    "Bybit_CATBNBUSDT_spot_1d": {
      "exchange": "Bybit",
      "symbol": "CATBNBUSDT",
      "market": "spot",
      "interval": "1d",
      "price": 6.19e-06,
      "signal_type": "bullish",
      "timestamp": "2025-06-15T02:34:05.968394+00:00"
    },
    "Bybit_HVHUSDT_spot_1d": {
      "exchange": "Bybit",
      "symbol": "HVHUSDT",
      "market": "spot",
      "interval": "1d",
      "price": 0.001117,
      "signal_type": "bullish",
      "timestamp": "2025-06-15T02:34:06.955489+00:00"
    },
    "Bybit_SONUSDT_spot_1d": {
      "exchange": "Bybit",
      "symbol": "SONUSDT",
      "market": "spot",
      "interval": "1d",
      "price": 6.47e-05,
      "signal_type": "bullish",
      "timestamp": "2025-06-15T02:34:07.951116+00:00"
    },
    "Bybit_FMBUSDT_spot_1M": {
      "exchange": "Bybit",
      "symbol": "FMBUSDT",
      "market": "spot",
      "interval": "1M",
      "price": 0.003967,
      "signal_type": "bullish",
      "timestamp": "2025-06-15T02:34:08.942184+00:00"
    },
    "Bybit_ACSUSDT_spot_1d": {
      "exchange": "Bybit",
      "symbol": "ACSUSDT",
      "market": "spot",
      "interval": "1d",
      "price": 0.0013331,
      "signal_type": "bullish",
      "timestamp": "2025-06-15T02:34:09.829496+00:00"
    },
    "Bybit_PAWSUSDT_spot_1M": {
      "exchange": "Bybit",
      "symbol": "PAWSUSDT",
      "market": "spot",
      "interval": "1M",
      "price": 0.0001261,
      "signal_type": "bearish",
      "timestamp": "2025-06-15T02:34:10.843726+00:00"
    },
    "Bybit_ZRCUSDT_spot_1M": {
      "exchange": "Bybit",
      "symbol": "ZRCUSDT",
      "market": "spot",
      "interval": "1M",
      "price": 0.03982,
      "signal_type": "bearish",
      "timestamp": "2025-06-15T02:34:11.808524+00:00"
    },
    "Bybit_SIDUSUSDT_spot_1d": {
      "exchange": "Bybit",
      "symbol": "SIDUSUSDT",
      "market": "spot",
      "interval": "1d",
      "price": 0.0008084,
      "signal_type": "bullish",
      "timestamp": "2025-06-15T02:34:12.787538+00:00"
    },
    "Bybit_AKIUSDT_spot_1w": {
      "exchange": "Bybit",
      "symbol": "AKIUSDT",
      "market": "spot",
      "interval": "1w",
      "price": 0.010722,
      "signal_type": "bearish",
      "timestamp": "2025-06-15T02:34:13.676134+00:00"
    },
    "Bybit_TENETUSDT_spot_1d": {
      "exchange": "Bybit",
      "symbol": "TENETUSDT",
      "market": "spot",
      "interval": "1d",
      "price": 0.0005285,
      "signal_type": "bullish",
      "timestamp": "2025-06-15T02:34:14.663239+00:00"
    },
    "Bybit_AFGUSDT_spot_1d": {
      "exchange": "Bybit",
      "symbol": "AFGUSDT",
      "market": "spot",
      "interval": "1d",
      "price": 0.003021,
      "signal_type": "bullish",
      "timestamp": "2025-06-15T02:34:15.630878+00:00"
    },
    "Bybit_FOXYUSDT_spot_1M": {
      "exchange": "Bybit",
      "symbol": "FOXYUSDT",
      "market": "spot",
      "interval": "1M",
      "price": 0.0026,
      "signal_type": "bearish",
      "timestamp": "2025-06-15T02:34:16.632132+00:00"
    },
    "Bybit_FMBUSDT_spot_1d": {
      "exchange": "Bybit",
      "symbol": "FMBUSDT",
      "market": "spot",
      "interval": "1d",
      "price": 0.008028,
      "signal_type": "bullish",
      "timestamp": "2025-06-15T02:34:17.483247+00:00"
    },
    "Bybit_XDCUSDT_spot_1M": {
      "exchange": "Bybit",
      "symbol": "XDCUSDT",
      "market": "spot",
      "interval": "1M",
      "price": 0.07738,
      "signal_type": "bearish",
      "timestamp": "2025-06-15T02:34:18.449176+00:00"
    },
    "Bybit_XETAUSDT_spot_1w": {
      "exchange": "Bybit",
      "symbol": "XETAUSDT",
      "market": "spot",
      "interval": "1w",
      "price": 0.0008211,
      "signal_type": "bearish",
      "timestamp": "2025-06-15T02:34:19.650667+00:00"
    },
    "Bybit_APTRUSDT_spot_1w": {
      "exchange": "Bybit",
      "symbol": "APTRUSDT",
      "market": "spot",
      "interval": "1w",
      "price": 0.001175,
      "signal_type": "bullish",
      "timestamp": "2025-06-15T02:34:20.866704+00:00"
    },
    "Bybit_ZRCUSDT_spot_1d": {
      "exchange": "Bybit",
      "symbol": "ZRCUSDT",
      "market": "spot",
      "interval": "1d",
      "price": 0.02723,
      "signal_type": "bullish",
      "timestamp": "2025-06-15T02:34:22.338420+00:00"
    },
    "Bybit_PIRATEUSDT_spot_1M": {
      "exchange": "Bybit",
      "symbol": "PIRATEUSDT",
      "market": "spot",
      "interval": "1M",
      "price": 0.04177,
      "signal_type": "bullish",
      "timestamp": "2025-06-15T02:34:23.328815+00:00"
    },
    "Bybit_PURSEUSDT_spot_1M": {
      "exchange": "Bybit",
      "symbol": "PURSEUSDT",
      "market": "spot",
      "interval": "1M",
      "price": 7.334e-05,
      "signal_type": "bearish",
      "timestamp": "2025-06-15T02:34:24.219671+00:00"
    },
    "Bybit_VELOUSDT_spot_1d": {
      "exchange": "Bybit",
      "symbol": "VELOUSDT",
      "market": "spot",
      "interval": "1d",
      "price": 0.013008,
      "signal_type": "bearish",
      "timestamp": "2025-06-15T02:34:25.204045+00:00"
    },
    "Bybit_PPTUSDT_spot_1M": {
      "exchange": "Bybit",
      "symbol": "PPTUSDT",
      "market": "spot",
      "interval": "1M",
      "price": 0.19342,
      "signal_type": "bullish",
      "timestamp": "2025-06-15T02:34:26.164236+00:00"
    },
    "Bybit_FOXYUSDT_spot_1d": {
      "exchange": "Bybit",
      "symbol": "FOXYUSDT",
      "market": "spot",
      "interval": "1d",
      "price": 0.001482,
      "signal_type": "bullish",
      "timestamp": "2025-06-15T02:34:27.166967+00:00"
    },
    "Bybit_AMIUSDT_spot_1d": {
      "exchange": "Bybit",
      "symbol": "AMIUSDT",
      "market": "spot",
      "interval": "1d",
      "price": 0.07914,
      "signal_type": "bearish",
      "timestamp": "2025-06-15T02:34:28.128850+00:00"
    },
    "Bybit_GENEUSDT_spot_1M": {
      "exchange": "Bybit",
      "symbol": "GENEUSDT",
      "market": "spot",
      "interval": "1M",
      "price": 0.05649,
      "signal_type": "bullish",
      "timestamp": "2025-06-15T02:34:29.146056+00:00"
    },
    "Bybit_CTAUSDT_spot_1M": {
      "exchange": "Bybit",
      "symbol": "CTAUSDT",
      "market": "spot",
      "interval": "1M",
      "price": 0.01946,
      "signal_type": "bullish",
      "timestamp": "2025-06-15T02:34:30.228047+00:00"
    },
    "Bybit_SATSUSDT_spot_1d": {
      "exchange": "Bybit",
      "symbol": "SATSUSDT",
      "market": "spot",
      "interval": "1d",
      "price": 4.094e-08,
      "signal_type": "bullish",
      "timestamp": "2025-06-15T02:34:31.214233+00:00"
    },
    "Bybit_PURSEUSDT_spot_1w": {
      "exchange": "Bybit",
      "symbol": "PURSEUSDT",
      "market": "spot",
      "interval": "1w",
      "price": 5.885e-05,
      "signal_type": "bearish",
      "timestamp": "2025-06-15T02:34:32.089301+00:00"
    },
    "Bybit_PSTAKEUSDT_spot_1d": {
      "exchange": "Bybit",
      "symbol": "PSTAKEUSDT",
      "market": "spot",
      "interval": "1d",
      "price": 0.03955,
      "signal_type": "bullish",
      "timestamp": "2025-06-15T02:34:33.087499+00:00"
    },
    "Bybit_PAALUSDT_spot_1M": {
      "exchange": "Bybit",
      "symbol": "PAALUSDT",
      "market": "spot",
      "interval": "1M",
      "price": 0.14756,
      "signal_type": "bearish",
      "timestamp": "2025-06-15T02:34:34.002225+00:00"
    },
    "Bybit_MAKUSDT_spot_1M": {
      "exchange": "Bybit",
      "symbol": "MAKUSDT",
      "market": "spot",
      "interval": "1M",
      "price": 0.00519,
      "signal_type": "bullish",
      "timestamp": "2025-06-15T02:34:34.966874+00:00"
    },
    "Bybit_WEMIXUSDT_spot_1M": {
      "exchange": "Bybit",
      "symbol": "WEMIXUSDT",
      "market": "spot",
      "interval": "1M",
      "price": 0.7334,
      "signal_type": "bearish",
      "timestamp": "2025-06-15T02:34:35.838493+00:00"
    },
    "Bybit_TAPUSDT_spot_1M": {
      "exchange": "Bybit",
      "symbol": "TAPUSDT",
      "market": "spot",
      "interval": "1M",
      "price": 0.0004122,
      "signal_type": "bearish",
      "timestamp": "2025-06-15T02:34:36.812251+00:00"
    },
    "Bybit_PURSEUSDT_spot_1d": {
      "exchange": "Bybit",
      "symbol": "PURSEUSDT",
      "market": "spot",
      "interval": "1d",
      "price": 5.452e-05,
      "signal_type": "bearish",
      "timestamp": "2025-06-15T02:34:37.727187+00:00"
    },
    "Bybit_GENEUSDT_spot_1d": {
      "exchange": "Bybit",
      "symbol": "GENEUSDT",
      "market": "spot",
      "interval": "1d",
      "price": 0.06549,
      "signal_type": "bearish",
      "timestamp": "2025-06-15T02:34:38.733417+00:00"
    },
    "Bybit_MBXUSDT_spot_1d": {
      "exchange": "Bybit",
      "symbol": "MBXUSDT",
      "market": "spot",
      "interval": "1d",
      "price": 0.1941,
      "signal_type": "bullish",
      "timestamp": "2025-06-15T02:34:39.654053+00:00"
    },
    "Bybit_MONUSDT_spot_1d": {
      "exchange": "Bybit",
      "symbol": "MONUSDT",
      "market": "spot",
      "interval": "1d",
      "price": 0.01904,
      "signal_type": "bullish",
      "timestamp": "2025-06-15T02:34:40.643857+00:00"
    },
    "Bybit_MAKUSDT_spot_1w": {
      "exchange": "Bybit",
      "symbol": "MAKUSDT",
      "market": "spot",
      "interval": "1w",
      "price": 0.006435,
      "signal_type": "bullish",
      "timestamp": "2025-06-15T02:34:41.508177+00:00"
    },
    "Bybit_WEMIXUSDT_spot_1w": {
      "exchange": "Bybit",
      "symbol": "WEMIXUSDT",
      "market": "spot",
      "interval": "1w",
      "price": 0.212,
      "signal_type": "bullish",
      "timestamp": "2025-06-15T02:34:42.518620+00:00"
    },
    "Bybit_SUPRAUSDT_spot_1M": {
      "exchange": "Bybit",
      "symbol": "SUPRAUSDT",
      "market": "spot",
      "interval": "1M",
      "price": 0.00683,
      "signal_type": "bearish",
      "timestamp": "2025-06-15T02:34:43.410849+00:00"
    },
    "Bybit_STARUSDT_spot_1d": {
      "exchange": "Bybit",
      "symbol": "STARUSDT",
      "market": "spot",
      "interval": "1d",
      "price": 0.006462,
      "signal_type": "bearish",
      "timestamp": "2025-06-15T02:34:44.395867+00:00"
    },
    "Bybit_NAVXUSDT_spot_1M": {
      "exchange": "Bybit",
      "symbol": "NAVXUSDT",
      "market": "spot",
      "interval": "1M",
      "price": 0.05823,
      "signal_type": "bearish",
      "timestamp": "2025-06-15T02:34:45.417874+00:00"
    },
    "Bybit_STETHUSDT_spot_1M": {
      "exchange": "Bybit",
      "symbol": "STETHUSDT",
      "market": "spot",
      "interval": "1M",
      "price": 1791.95,
      "signal_type": "bullish",
      "timestamp": "2025-06-15T02:34:46.387438+00:00"
    },
    "Bybit_PAALUSDT_spot_1d": {
      "exchange": "Bybit",
      "symbol": "PAALUSDT",
      "market": "spot",
      "interval": "1d",
      "price": 0.11423,
      "signal_type": "bearish",
      "timestamp": "2025-06-15T02:34:47.655990+00:00"
    },
    "Bybit_MAKUSDT_spot_1d": {
      "exchange": "Bybit",
      "symbol": "MAKUSDT",
      "market": "spot",
      "interval": "1d",
      "price": 0.006809,
      "signal_type": "bullish",
      "timestamp": "2025-06-15T02:34:48.648817+00:00"
    },
    "Bybit_USDTBUSDT_spot_1d": {
      "exchange": "Bybit",
      "symbol": "USDTBUSDT",
      "market": "spot",
      "interval": "1d",
      "price": 0.9999,
      "signal_type": "bullish",
      "timestamp": "2025-06-15T02:34:49.631009+00:00"
    },
    "Bybit_SFUNDUSDT_spot_1w": {
      "exchange": "Bybit",
      "symbol": "SFUNDUSDT",
      "market": "spot",
      "interval": "1w",
      "price": 0.6665,
      "signal_type": "bullish",
      "timestamp": "2025-06-15T02:34:50.626306+00:00"
    },
    "Bybit_XTERUSDT_spot_1w": {
      "exchange": "Bybit",
      "symbol": "XTERUSDT",
      "market": "spot",
      "interval": "1w",
      "price": 0.23461,
      "signal_type": "bearish",
      "timestamp": "2025-06-15T02:34:51.507633+00:00"
    },
    "Bybit_TAPUSDT_spot_1d": {
      "exchange": "Bybit",
      "symbol": "TAPUSDT",
      "market": "spot",
      "interval": "1d",
      "price": 0.0003421,
      "signal_type": "bullish",
      "timestamp": "2025-06-15T02:34:53.472739+00:00"
    },
    "Bybit_SUPRAUSDT_spot_1d": {
      "exchange": "Bybit",
      "symbol": "SUPRAUSDT",
      "market": "spot",
      "interval": "1d",
      "price": 0.00386,
      "signal_type": "bullish",
      "timestamp": "2025-06-15T02:34:54.423342+00:00"
    },
    "Bybit_TOSHIUSDT_spot_1d": {
      "exchange": "Bybit",
      "symbol": "TOSHIUSDT",
      "market": "spot",
      "interval": "1d",
      "price": 0.00054033,
      "signal_type": "bearish",
      "timestamp": "2025-06-15T02:34:55.388773+00:00"
    },
    "Bybit_XTERUSDT_spot_1d": {
      "exchange": "Bybit",
      "symbol": "XTERUSDT",
      "market": "spot",
      "interval": "1d",
      "price": 0.17888,
      "signal_type": "bearish",
      "timestamp": "2025-06-15T02:34:56.411335+00:00"
    }
  }
}